hex_zmq_servers/__init__.py
hex_zmq_servers/device_base.py
hex_zmq_servers/hex_launch.py
hex_zmq_servers/zmq_base.py
hex_zmq_servers/cam/__init__.py
hex_zmq_servers/cam/cam_base.py
hex_zmq_servers/cam/berxel/__init__.py
hex_zmq_servers/cam/berxel/cam_berxel.py
hex_zmq_servers/cam/berxel/cam_berxel_cli.py
hex_zmq_servers/cam/berxel/cam_berxel_srv.py
hex_zmq_servers/cam/dummy/__init__.py
hex_zmq_servers/cam/dummy/cam_dummy.py
hex_zmq_servers/cam/dummy/cam_dummy_cli.py
hex_zmq_servers/cam/dummy/cam_dummy_srv.py
hex_zmq_servers/cam/realsense/__init__.py
hex_zmq_servers/cam/realsense/cam_realsense.py
hex_zmq_servers/cam/realsense/cam_realsense_cli.py
hex_zmq_servers/cam/realsense/cam_realsense_srv.py
hex_zmq_servers/cam/rgb/__init__.py
hex_zmq_servers/cam/rgb/cam_rgb.py
hex_zmq_servers/cam/rgb/cam_rgb_cli.py
hex_zmq_servers/cam/rgb/cam_rgb_srv.py
hex_zmq_servers/config/cam_berxel.json
hex_zmq_servers/config/cam_dummy.json
hex_zmq_servers/config/cam_realsense.json
hex_zmq_servers/config/cam_rgb.json
hex_zmq_servers/config/mujoco_archer_y6.json
hex_zmq_servers/config/mujoco_e3_desktop.json
hex_zmq_servers/config/robot_dummy.json
hex_zmq_servers/config/robot_gello.json
hex_zmq_servers/config/robot_hexarm.json
hex_zmq_servers/config/zmq_dummy.json
hex_zmq_servers/mujoco/__init__.py
hex_zmq_servers/mujoco/mujoco_base.py
hex_zmq_servers/mujoco/archer_y6/__init__.py
hex_zmq_servers/mujoco/archer_y6/mujoco_archer_y6.py
hex_zmq_servers/mujoco/archer_y6/mujoco_archer_y6_cli.py
hex_zmq_servers/mujoco/archer_y6/mujoco_archer_y6_srv.py
hex_zmq_servers/mujoco/archer_y6/model/joint_class.xml
hex_zmq_servers/mujoco/archer_y6/model/robot.xml
hex_zmq_servers/mujoco/archer_y6/model/scene.xml
hex_zmq_servers/mujoco/archer_y6/model/setting.xml
hex_zmq_servers/mujoco/archer_y6/model/assets/arm_base_link.STL
hex_zmq_servers/mujoco/archer_y6/model/assets/arm_link_1.STL
hex_zmq_servers/mujoco/archer_y6/model/assets/arm_link_2.STL
hex_zmq_servers/mujoco/archer_y6/model/assets/arm_link_3.STL
hex_zmq_servers-0.3.16.dist-info/licenses/LICENSE
hex_zmq_servers-0.3.16.dist-info/METADATA
hex_zmq_servers-0.3.16.dist-info/WHEEL
hex_zmq_servers-0.3.16.dist-info/top_level.txt
hex_zmq_servers-0.3.16.dist-info/RECORD
