Metadata-Version: 2.4
Name: hex_zmq_servers
Version: 0.3.16
Summary: HEXFELLOW ZMQ Servers
Author-email: Dong Zhaorui <joray.dong@hexfellow.com>
Maintainer-email: jecjune <zejun.chen@hexfellow.com>, Dong Zhaorui <joray.dong@hexfellow.com>
License-Expression: Apache-2.0
Project-URL: Homepage, https://github.com/hexfellow/hex_zmq_servers
Project-URL: Repository, https://github.com/hexfellow/hex_zmq_servers.git
Project-URL: Bug Tracker, https://github.com/hexfellow/hex_zmq_servers/issues
Project-URL: Documentation, https://github.com/hexfellow/hex_zmq_servers/wiki
Keywords: hex_zmq_servers
Classifier: Development Status :: 4 - Beta
Classifier: Intended Audience :: Developers
Classifier: Intended Audience :: Science/Research
Classifier: Topic :: Software Development :: Libraries :: Python Modules
Classifier: Programming Language :: Python :: 3
Classifier: Programming Language :: Python :: 3.10
Classifier: Programming Language :: Python :: 3.11
Classifier: Programming Language :: Python :: 3.12
Classifier: Operating System :: POSIX :: Linux
Requires-Python: >=3.10
License-File: LICENSE
Requires-Dist: pyzmq>=27.0.1
Requires-Dist: hex_device<1.4.0,>=1.3.1
Requires-Dist: hex_robo_utils<0.3.0,>=0.2.0
Requires-Dist: dynamixel-sdk==3.8.4
Requires-Dist: opencv-python>=4.2
Provides-Extra: berxel
Requires-Dist: berxel_py_wrapper>=2.0.182; extra == "berxel"
Provides-Extra: realsense
Requires-Dist: pyrealsense2>=2.56.5.9235; extra == "realsense"
Provides-Extra: mujoco
Requires-Dist: mujoco>=3.3.3; extra == "mujoco"
Provides-Extra: all
Requires-Dist: berxel_py_wrapper>=2.0.182; extra == "all"
Requires-Dist: mujoco>=3.3.3; extra == "all"
Requires-Dist: pyrealsense2>=2.56.5.9235; extra == "all"
Dynamic: license-file
